smart_locators_playwright/__init__.py
smart_locators_playwright/custom_exceptions.py
smart_locators_playwright/smart_locators.py
smart_locators_playwright-1.0.0.dist-info/licenses/LICENSE
smart_locators_playwright-1.0.0.dist-info/METADATA
smart_locators_playwright-1.0.0.dist-info/WHEEL
smart_locators_playwright-1.0.0.dist-info/top_level.txt
smart_locators_playwright-1.0.0.dist-info/RECORD
