Metadata-Version: 2.4
Name: smart-locators-playwright
Version: 1.0.0
Summary: A simplified Python-playwright utility that provides more flexible locator strategies which is easier for users.
Home-page: https://github.com/thereal-manish/smart-locators-playwright/
Author: Manikandan Baskaran
Author-email: manikandan.baskaran.15@gmail.com
Classifier: Programming Language :: Python :: 3
Classifier: License :: OSI Approved :: Apache Software License
Classifier: Operating System :: OS Independent
Requires-Python: >=3
License-File: LICENSE
Requires-Dist: playwright
Dynamic: author
Dynamic: author-email
Dynamic: classifier
Dynamic: description
Dynamic: description-content-type
Dynamic: home-page
Dynamic: license-file
Dynamic: requires-dist
Dynamic: requires-python
Dynamic: summary
